odoo8_addon_logistic_order_donation_budget-8.0.0.1.0-py2.7-nspkg.pth
odoo_addons/logistic_order_donation_budget/__openerp__.py
odoo_addons/logistic_order_donation_budget/__init__.py
odoo_addons/logistic_order_donation_budget/README.rst
odoo_addons/logistic_order_donation_budget/model/sale_order.py
odoo_addons/logistic_order_donation_budget/model/__init__.py
odoo_addons/logistic_order_donation_budget/demo/donation.xml
odoo8_addon_logistic_order_donation_budget-8.0.0.1.0.dist-info/top_level.txt
odoo8_addon_logistic_order_donation_budget-8.0.0.1.0.dist-info/WHEEL
odoo8_addon_logistic_order_donation_budget-8.0.0.1.0.dist-info/RECORD
odoo8_addon_logistic_order_donation_budget-8.0.0.1.0.dist-info/metadata.json
odoo8_addon_logistic_order_donation_budget-8.0.0.1.0.dist-info/DESCRIPTION.rst
odoo8_addon_logistic_order_donation_budget-8.0.0.1.0.dist-info/METADATA
odoo8_addon_logistic_order_donation_budget-8.0.0.1.0.dist-info/namespace_packages.txt
